aws_service_mcp_generator/__init__.py
aws_service_mcp_generator/generator.py
aws_service_mcp_generator-2.0.3.dist-info/METADATA
aws_service_mcp_generator-2.0.3.dist-info/WHEEL
aws_service_mcp_generator-2.0.3.dist-info/RECORD
